astor/__init__.py
astor/code_gen.py
astor/codegen.py
astor/file_util.py
astor/node_util.py
astor/op_util.py
astor/rtrip.py
astor/source_repr.py
astor/string_repr.py
astor/tree_walk.py
astor-0.8.0.dist-info/AUTHORS
astor-0.8.0.dist-info/LICENSE
astor-0.8.0.dist-info/METADATA
astor-0.8.0.dist-info/WHEEL
astor-0.8.0.dist-info/top_level.txt
astor-0.8.0.dist-info/zip-safe
astor-0.8.0.dist-info/RECORD
